robust/__init__.py
robust/main.py
robust_black_zer_0-1.2.dist-info/licenses/LICENSE
robust_black_zer_0-1.2.dist-info/METADATA
robust_black_zer_0-1.2.dist-info/WHEEL
robust_black_zer_0-1.2.dist-info/entry_points.txt
robust_black_zer_0-1.2.dist-info/top_level.txt
robust_black_zer_0-1.2.dist-info/RECORD
