Metadata-Version: 2.4
Name: robust-Black-Zer-0
Version: 1.2
Summary: A powerful tool by BLACK ZERO
Home-page: https://github.com/BLACK-ZER-0/robust
Author: BLACK-ZER-0
License: MIT
License-File: LICENSE
Requires-Dist: requests
Requires-Dist: aiohttp
Requires-Dist: rich
Dynamic: author
Dynamic: description
Dynamic: description-content-type
Dynamic: home-page
Dynamic: license
Dynamic: license-file
Dynamic: requires-dist
Dynamic: summary
